pytest_austin/__init__.py
pytest_austin/markers.py
pytest_austin/plugin.py
pytest_austin-0.1.0.dist-info/entry_points.txt
pytest_austin-0.1.0.dist-info/LICENSE
pytest_austin-0.1.0.dist-info/WHEEL
pytest_austin-0.1.0.dist-info/METADATA
pytest_austin-0.1.0.dist-info/RECORD
