Metadata-Version: 2.1
Name: pytest-austin
Version: 0.1.0
Summary: Austin plugin for pytest
Home-page: https://github.com/P403n1x87/pytest-austin
License: GPL-3.0-or-later
Keywords: performance,profiling,testing,development
Author: Gabriele N. Tornetta
Author-email: phoenix1987@gmail.com
Requires-Python: >=3.6,<4.0
Classifier: Development Status :: 4 - Beta
Classifier: Framework :: Pytest
Classifier: Intended Audience :: Developers
Classifier: License :: OSI Approved :: GNU General Public License v3 or later (GPLv3+)
Classifier: Programming Language :: Python :: 3
Classifier: Programming Language :: Python :: 3.6
Classifier: Programming Language :: Python :: 3.7
Classifier: Programming Language :: Python :: 3.8
Classifier: Programming Language :: Python :: 3.9
Requires-Dist: ansimarkup (>=1.4.0,<2.0.0)
Requires-Dist: austin-python (>=0.1.0,<0.2.0)
Requires-Dist: dataclasses
Requires-Dist: psutil (>=5.7.0)
Project-URL: Repository, https://github.com/P403n1x87/pytest-austin
Project-URL: issues, https://github.com/P403n1x87/pytest-austin/issues
